[
  {
    "loc_id": 884,
    "loc_no": "01400336",
    "facilityDetails": {
      "facilityId": "01400336",
      "legalName": "Kroger Limited Partnership I",
      "vanityName": "Monroe",
      "address": {
        "address1": "3033 Heritage Green Dr",
        "address2": "",
        "city": "Monroe",
        "state": "OH",
        "zipCode": "45050"
      },
      "distance": 7.574940596035599,
      "phone": {
        "countryCode": "",
        "areaCode": "513",
        "phoneNumber": "7277440",
        "extension": ""
      },
      "onlinePaymentsEnabled": true,
      "onlineOrderingEnabled": false,
      "pharmacyHours": {
        "sundayClose": "18:00",
        "sundayOpen": "11:00",
        "sundayHours": "",
        "mondayClose": "21:00",
        "mondayOpen": "09:00",
        "mondayHours": "",
        "tuesdayClose": "21:00",
        "tuesdayOpen": "09:00",
        "tuesdayHours": "",
        "wednesdayClose": "21:00",
        "wednesdayOpen": "09:00",
        "wednesdayHours": "",
        "thursdayClose": "21:00",
        "thursdayOpen": "09:00",
        "thursdayHours": "",
        "fridayClose": "21:00",
        "fridayOpen": "09:00",
        "fridayHours": "",
        "saturdayClose": "18:00",
        "saturdayOpen": "10:00",
        "saturdayHours": ""
      },
      "brand": "KROGER"
    },
    "dates": [
      {
        "date": "2021-03-18",
        "slots": []
      },
      {
        "date": "2021-03-19",
        "slots": []
      },
      {
        "date": "2021-03-20",
        "slots": []
      },
      {
        "date": "2021-03-21",
        "slots": []
      },
      {
        "date": "2021-03-22",
        "slots": []
      },
      {
        "date": "2021-03-23",
        "slots": []
      },
      {
        "date": "2021-03-24",
        "slots": []
      },
      {
        "date": "2021-03-25",
        "slots": []
      },
      {
        "date": "2021-03-26",
        "slots": []
      },
      {
        "date": "2021-03-27",
        "slots": []
      },
      {
        "date": "2021-03-28",
        "slots": []
      },
      {
        "date": "2021-03-29",
        "slots": []
      },
      {
        "date": "2021-03-30",
        "slots": []
      },
      {
        "date": "2021-03-31",
        "slots": []
      },
      {
        "date": "2021-04-01",
        "slots": []
      }
    ]
  },
  {
    "loc_id": 886,
    "loc_no": "01400351",
    "facilityDetails": {
      "facilityId": "01400351",
      "legalName": "Kroger Limited Partnership I",
      "vanityName": "Montgomery",
      "address": {
        "address1": "9939 Montgomery Rd",
        "address2": "",
        "city": "Montgomery",
        "state": "OH",
        "zipCode": "45242"
      },
      "distance": 7.657863260136741,
      "phone": {
        "countryCode": "",
        "areaCode": "513",
        "phoneNumber": "7931620",
        "extension": ""
      },
      "onlinePaymentsEnabled": true,
      "onlineOrderingEnabled": false,
      "pharmacyHours": {
        "sundayClose": "18:00",
        "sundayOpen": "11:00",
        "sundayHours": "",
        "mondayClose": "21:00",
        "mondayOpen": "09:00",
        "mondayHours": "",
        "tuesdayClose": "21:00",
        "tuesdayOpen": "09:00",
        "tuesdayHours": "",
        "wednesdayClose": "21:00",
        "wednesdayOpen": "09:00",
        "wednesdayHours": "",
        "thursdayClose": "21:00",
        "thursdayOpen": "09:00",
        "thursdayHours": "",
        "fridayClose": "21:00",
        "fridayOpen": "09:00",
        "fridayHours": "",
        "saturdayClose": "18:00",
        "saturdayOpen": "10:00",
        "saturdayHours": ""
      },
      "brand": "KROGER"
    },
    "dates": [
      {
        "date": "2021-03-18",
        "slots": []
      },
      {
        "date": "2021-03-19",
        "slots": []
      },
      {
        "date": "2021-03-20",
        "slots": []
      },
      {
        "date": "2021-03-21",
        "slots": []
      },
      {
        "date": "2021-03-22",
        "slots": []
      },
      {
        "date": "2021-03-23",
        "slots": []
      },
      {
        "date": "2021-03-24",
        "slots": []
      },
      {
        "date": "2021-03-25",
        "slots": []
      },
      {
        "date": "2021-03-26",
        "slots": []
      },
      {
        "date": "2021-03-27",
        "slots": []
      },
      {
        "date": "2021-03-28",
        "slots": []
      },
      {
        "date": "2021-03-29",
        "slots": []
      },
      {
        "date": "2021-03-30",
        "slots": []
      },
      {
        "date": "2021-03-31",
        "slots": []
      },
      {
        "date": "2021-04-01",
        "slots": []
      }
    ]
  },
  {
    "loc_id": 887,
    "loc_no": "01400353",
    "facilityDetails": {
      "facilityId": "01400353",
      "legalName": "Kroger Limited Partnership I",
      "vanityName": "Harpers Point",
      "address": {
        "address1": "11390 Montgomery Rd",
        "address2": "",
        "city": "Cincinnati",
        "state": "OH",
        "zipCode": "45249"
      },
      "distance": 5.128210405582525,
      "phone": {
        "countryCode": "",
        "areaCode": "513",
        "phoneNumber": "2477760",
        "extension": ""
      },
      "onlinePaymentsEnabled": true,
      "onlineOrderingEnabled": false,
      "pharmacyHours": {
        "sundayClose": "18:00",
        "sundayOpen": "10:00",
        "sundayHours": "",
        "mondayClose": "21:00",
        "mondayOpen": "09:00",
        "mondayHours": "",
        "tuesdayClose": "21:00",
        "tuesdayOpen": "09:00",
        "tuesdayHours": "",
        "wednesdayClose": "21:00",
        "wednesdayOpen": "09:00",
        "wednesdayHours": "",
        "thursdayClose": "21:00",
        "thursdayOpen": "09:00",
        "thursdayHours": "",
        "fridayClose": "21:00",
        "fridayOpen": "09:00",
        "fridayHours": "",
        "saturdayClose": "18:00",
        "saturdayOpen": "10:00",
        "saturdayHours": ""
      },
      "brand": "KROGER"
    },
    "dates": [
      {
        "date": "2021-03-18",
        "slots": []
      },
      {
        "date": "2021-03-19",
        "slots": []
      },
      {
        "date": "2021-03-20",
        "slots": []
      },
      {
        "date": "2021-03-21",
        "slots": []
      },
      {
        "date": "2021-03-22",
        "slots": []
      },
      {
        "date": "2021-03-23",
        "slots": []
      },
      {
        "date": "2021-03-24",
        "slots": []
      },
      {
        "date": "2021-03-25",
        "slots": []
      },
      {
        "date": "2021-03-26",
        "slots": []
      },
      {
        "date": "2021-03-27",
        "slots": []
      },
      {
        "date": "2021-03-28",
        "slots": []
      },
      {
        "date": "2021-03-29",
        "slots": []
      },
      {
        "date": "2021-03-30",
        "slots": []
      },
      {
        "date": "2021-03-31",
        "slots": []
      },
      {
        "date": "2021-04-01",
        "slots": []
      }
    ]
  },
  {
    "loc_id": 894,
    "loc_no": "01400376",
    "facilityDetails": {
      "facilityId": "01400376",
      "legalName": "Kroger Limited Partnership I",
      "vanityName": "Landen",
      "address": {
        "address1": "2900 W. St. Rt. 22 & 3",
        "address2": "",
        "city": "Maineville",
        "state": "OH",
        "zipCode": "45039"
      },
      "distance": 3.096792518453793,
      "phone": {
        "countryCode": "",
        "areaCode": "513",
        "phoneNumber": "6834224",
        "extension": ""
      },
      "onlinePaymentsEnabled": true,
      "onlineOrderingEnabled": false,
      "pharmacyHours": {
        "sundayClose": "18:00",
        "sundayOpen": "11:00",
        "sundayHours": "",
        "mondayClose": "21:00",
        "mondayOpen": "09:00",
        "mondayHours": "",
        "tuesdayClose": "21:00",
        "tuesdayOpen": "09:00",
        "tuesdayHours": "",
        "wednesdayClose": "21:00",
        "wednesdayOpen": "09:00",
        "wednesdayHours": "",
        "thursdayClose": "21:00",
        "thursdayOpen": "09:00",
        "thursdayHours": "",
        "fridayClose": "21:00",
        "fridayOpen": "09:00",
        "fridayHours": "",
        "saturdayClose": "18:00",
        "saturdayOpen": "10:00",
        "saturdayHours": ""
      },
      "brand": "KROGER"
    },
    "dates": [
      {
        "date": "2021-03-18",
        "slots": []
      },
      {
        "date": "2021-03-19",
        "slots": []
      },
      {
        "date": "2021-03-20",
        "slots": []
      },
      {
        "date": "2021-03-21",
        "slots": []
      },
      {
        "date": "2021-03-22",
        "slots": []
      },
      {
        "date": "2021-03-23",
        "slots": []
      },
      {
        "date": "2021-03-24",
        "slots": []
      },
      {
        "date": "2021-03-25",
        "slots": []
      },
      {
        "date": "2021-03-26",
        "slots": []
      },
      {
        "date": "2021-03-27",
        "slots": []
      },
      {
        "date": "2021-03-28",
        "slots": []
      },
      {
        "date": "2021-03-29",
        "slots": []
      },
      {
        "date": "2021-03-30",
        "slots": []
      },
      {
        "date": "2021-03-31",
        "slots": []
      },
      {
        "date": "2021-04-01",
        "slots": []
      }
    ]
  },
  {
    "loc_id": 897,
    "loc_no": "01400383",
    "facilityDetails": {
      "facilityId": "01400383",
      "legalName": "Kroger Limited Partnership I",
      "vanityName": "Liberty Township, OH Marketplace",
      "address": {
        "address1": "7300 Yankee Rd",
        "address2": "",
        "city": "Liberty Township",
        "state": "OH",
        "zipCode": "45044"
      },
      "distance": 4.044698028767011,
      "phone": {
        "countryCode": "",
        "areaCode": "513",
        "phoneNumber": "3423260",
        "extension": ""
      },
      "onlinePaymentsEnabled": true,
      "onlineOrderingEnabled": false,
      "pharmacyHours": {
        "sundayClose": "18:00",
        "sundayOpen": "10:00",
        "sundayHours": "",
        "mondayClose": "21:00",
        "mondayOpen": "09:00",
        "mondayHours": "",
        "tuesdayClose": "21:00",
        "tuesdayOpen": "09:00",
        "tuesdayHours": "",
        "wednesdayClose": "21:00",
        "wednesdayOpen": "09:00",
        "wednesdayHours": "",
        "thursdayClose": "21:00",
        "thursdayOpen": "09:00",
        "thursdayHours": "",
        "fridayClose": "21:00",
        "fridayOpen": "09:00",
        "fridayHours": "",
        "saturdayClose": "18:00",
        "saturdayOpen": "10:00",
        "saturdayHours": ""
      },
      "brand": "KROGER"
    },
    "dates": [
      {
        "date": "2021-03-18",
        "slots": []
      },
      {
        "date": "2021-03-19",
        "slots": []
      },
      {
        "date": "2021-03-20",
        "slots": []
      },
      {
        "date": "2021-03-21",
        "slots": []
      },
      {
        "date": "2021-03-22",
        "slots": []
      },
      {
        "date": "2021-03-23",
        "slots": []
      },
      {
        "date": "2021-03-24",
        "slots": []
      },
      {
        "date": "2021-03-25",
        "slots": []
      },
      {
        "date": "2021-03-26",
        "slots": []
      },
      {
        "date": "2021-03-27",
        "slots": []
      },
      {
        "date": "2021-03-28",
        "slots": []
      },
      {
        "date": "2021-03-29",
        "slots": []
      },
      {
        "date": "2021-03-30",
        "slots": []
      },
      {
        "date": "2021-03-31",
        "slots": []
      },
      {
        "date": "2021-04-01",
        "slots": []
      }
    ]
  },
  {
    "loc_id": 905,
    "loc_no": "01400408",
    "facilityDetails": {
      "facilityId": "01400408",
      "legalName": "Kroger Limited Partnership I",
      "vanityName": "Maineville",
      "address": {
        "address1": "5705 S State Route 48",
        "address2": "",
        "city": "Maineville",
        "state": "OH",
        "zipCode": "45039"
      },
      "distance": 4.939777777844698,
      "phone": {
        "countryCode": "",
        "areaCode": "513",
        "phoneNumber": "4942215",
        "extension": ""
      },
      "onlinePaymentsEnabled": true,
      "onlineOrderingEnabled": false,
      "pharmacyHours": {
        "sundayClose": "18:00",
        "sundayOpen": "10:00",
        "sundayHours": "",
        "mondayClose": "21:00",
        "mondayOpen": "09:00",
        "mondayHours": "",
        "tuesdayClose": "21:00",
        "tuesdayOpen": "09:00",
        "tuesdayHours": "",
        "wednesdayClose": "21:00",
        "wednesdayOpen": "09:00",
        "wednesdayHours": "",
        "thursdayClose": "21:00",
        "thursdayOpen": "09:00",
        "thursdayHours": "",
        "fridayClose": "21:00",
        "fridayOpen": "09:00",
        "fridayHours": "",
        "saturdayClose": "18:00",
        "saturdayOpen": "10:00",
        "saturdayHours": ""
      },
      "brand": "KROGER"
    },
    "dates": [
      {
        "date": "2021-03-18",
        "slots": []
      },
      {
        "date": "2021-03-19",
        "slots": []
      },
      {
        "date": "2021-03-20",
        "slots": []
      },
      {
        "date": "2021-03-21",
        "slots": []
      },
      {
        "date": "2021-03-22",
        "slots": []
      },
      {
        "date": "2021-03-23",
        "slots": []
      },
      {
        "date": "2021-03-24",
        "slots": []
      },
      {
        "date": "2021-03-25",
        "slots": []
      },
      {
        "date": "2021-03-26",
        "slots": []
      },
      {
        "date": "2021-03-27",
        "slots": []
      },
      {
        "date": "2021-03-28",
        "slots": []
      },
      {
        "date": "2021-03-29",
        "slots": []
      },
      {
        "date": "2021-03-30",
        "slots": []
      },
      {
        "date": "2021-03-31",
        "slots": []
      },
      {
        "date": "2021-04-01",
        "slots": []
      }
    ]
  },
  {
    "loc_id": 910,
    "loc_no": "01400413",
    "facilityDetails": {
      "facilityId": "01400413",
      "legalName": "Kroger Limited Partnership I",
      "vanityName": "Loveland",
      "address": {
        "address1": "800 Loveland Madeira Rd",
        "address2": "",
        "city": "Loveland",
        "state": "OH",
        "zipCode": "45140"
      },
      "distance": 6.16819035829887,
      "phone": {
        "countryCode": "",
        "areaCode": "513",
        "phoneNumber": "6773400",
        "extension": ""
      },
      "onlinePaymentsEnabled": true,
      "onlineOrderingEnabled": false,
      "pharmacyHours": {
        "sundayClose": "18:00",
        "sundayOpen": "11:00",
        "sundayHours": "",
        "mondayClose": "21:00",
        "mondayOpen": "09:00",
        "mondayHours": "",
        "tuesdayClose": "21:00",
        "tuesdayOpen": "09:00",
        "tuesdayHours": "",
        "wednesdayClose": "21:00",
        "wednesdayOpen": "09:00",
        "wednesdayHours": "",
        "thursdayClose": "21:00",
        "thursdayOpen": "09:00",
        "thursdayHours": "",
        "fridayClose": "21:00",
        "fridayOpen": "09:00",
        "fridayHours": "",
        "saturdayClose": "18:00",
        "saturdayOpen": "10:00",
        "saturdayHours": ""
      },
      "brand": "KROGER"
    },
    "dates": [
      {
        "date": "2021-03-18",
        "slots": []
      },
      {
        "date": "2021-03-19",
        "slots": []
      },
      {
        "date": "2021-03-20",
        "slots": []
      },
      {
        "date": "2021-03-21",
        "slots": []
      },
      {
        "date": "2021-03-22",
        "slots": []
      },
      {
        "date": "2021-03-23",
        "slots": []
      },
      {
        "date": "2021-03-24",
        "slots": []
      },
      {
        "date": "2021-03-25",
        "slots": []
      },
      {
        "date": "2021-03-26",
        "slots": []
      },
      {
        "date": "2021-03-27",
        "slots": []
      },
      {
        "date": "2021-03-28",
        "slots": []
      },
      {
        "date": "2021-03-29",
        "slots": []
      },
      {
        "date": "2021-03-30",
        "slots": []
      },
      {
        "date": "2021-03-31",
        "slots": []
      },
      {
        "date": "2021-04-01",
        "slots": []
      }
    ]
  },
  {
    "loc_id": 915,
    "loc_no": "01400426",
    "facilityDetails": {
      "facilityId": "01400426",
      "legalName": "Kroger Limited Partnership I",
      "vanityName": "Kings Mills Mason",
      "address": {
        "address1": "5210 State Route 741",
        "address2": "",
        "city": "Mason",
        "state": "OH",
        "zipCode": "45040"
      },
      "distance": 2.1113989787874208,
      "phone": {
        "countryCode": "",
        "areaCode": "513",
        "phoneNumber": "3988820",
        "extension": ""
      },
      "onlinePaymentsEnabled": true,
      "onlineOrderingEnabled": false,
      "pharmacyHours": {
        "sundayClose": "18:00",
        "sundayOpen": "11:00",
        "sundayHours": "",
        "mondayClose": "21:00",
        "mondayOpen": "09:00",
        "mondayHours": "",
        "tuesdayClose": "21:00",
        "tuesdayOpen": "09:00",
        "tuesdayHours": "",
        "wednesdayClose": "21:00",
        "wednesdayOpen": "09:00",
        "wednesdayHours": "",
        "thursdayClose": "21:00",
        "thursdayOpen": "09:00",
        "thursdayHours": "",
        "fridayClose": "21:00",
        "fridayOpen": "09:00",
        "fridayHours": "",
        "saturdayClose": "18:00",
        "saturdayOpen": "10:00",
        "saturdayHours": ""
      },
      "brand": "KROGER"
    },
    "dates": [
      {
        "date": "2021-03-18",
        "slots": []
      },
      {
        "date": "2021-03-19",
        "slots": []
      },
      {
        "date": "2021-03-20",
        "slots": []
      },
      {
        "date": "2021-03-21",
        "slots": []
      },
      {
        "date": "2021-03-22",
        "slots": []
      },
      {
        "date": "2021-03-23",
        "slots": []
      },
      {
        "date": "2021-03-24",
        "slots": []
      },
      {
        "date": "2021-03-25",
        "slots": []
      },
      {
        "date": "2021-03-26",
        "slots": []
      },
      {
        "date": "2021-03-27",
        "slots": []
      },
      {
        "date": "2021-03-28",
        "slots": []
      },
      {
        "date": "2021-03-29",
        "slots": []
      },
      {
        "date": "2021-03-30",
        "slots": []
      },
      {
        "date": "2021-03-31",
        "slots": []
      },
      {
        "date": "2021-04-01",
        "slots": []
      }
    ]
  },
  {
    "loc_id": 917,
    "loc_no": "01400429",
    "facilityDetails": {
      "facilityId": "01400429",
      "legalName": "Kroger Limited Partnership I",
      "vanityName": "Sharonville, OH",
      "address": {
        "address1": "12164 Lebanon Rd",
        "address2": "",
        "city": "Cincinnati",
        "state": "OH",
        "zipCode": "45241"
      },
      "distance": 5.310443618150823,
      "phone": {
        "countryCode": "",
        "areaCode": "513",
        "phoneNumber": "7334945",
        "extension": ""
      },
      "onlinePaymentsEnabled": true,
      "onlineOrderingEnabled": false,
      "pharmacyHours": {
        "sundayClose": "18:00",
        "sundayOpen": "11:00",
        "sundayHours": "",
        "mondayClose": "21:00",
        "mondayOpen": "09:00",
        "mondayHours": "",
        "tuesdayClose": "21:00",
        "tuesdayOpen": "09:00",
        "tuesdayHours": "",
        "wednesdayClose": "21:00",
        "wednesdayOpen": "09:00",
        "wednesdayHours": "",
        "thursdayClose": "21:00",
        "thursdayOpen": "09:00",
        "thursdayHours": "",
        "fridayClose": "21:00",
        "fridayOpen": "09:00",
        "fridayHours": "",
        "saturdayClose": "18:00",
        "saturdayOpen": "10:00",
        "saturdayHours": ""
      },
      "brand": "KROGER"
    },
    "dates": [
      {
        "date": "2021-03-18",
        "slots": []
      },
      {
        "date": "2021-03-19",
        "slots": []
      },
      {
        "date": "2021-03-20",
        "slots": []
      },
      {
        "date": "2021-03-21",
        "slots": []
      },
      {
        "date": "2021-03-22",
        "slots": []
      },
      {
        "date": "2021-03-23",
        "slots": []
      },
      {
        "date": "2021-03-24",
        "slots": []
      },
      {
        "date": "2021-03-25",
        "slots": []
      },
      {
        "date": "2021-03-26",
        "slots": []
      },
      {
        "date": "2021-03-27",
        "slots": []
      },
      {
        "date": "2021-03-28",
        "slots": []
      },
      {
        "date": "2021-03-29",
        "slots": []
      },
      {
        "date": "2021-03-30",
        "slots": []
      },
      {
        "date": "2021-03-31",
        "slots": []
      },
      {
        "date": "2021-04-01",
        "slots": []
      }
    ]
  },
  {
    "loc_id": 923,
    "loc_no": "01400435",
    "facilityDetails": {
      "facilityId": "01400435",
      "legalName": "Kroger Limited Partnership I",
      "vanityName": "Miami Township",
      "address": {
        "address1": "6388 Branch Hill Guinea Pike",
        "address2": "",
        "city": "Loveland",
        "state": "OH",
        "zipCode": "45140"
      },
      "distance": 8.56709403109046,
      "phone": {
        "countryCode": "",
        "areaCode": "513",
        "phoneNumber": "6974820",
        "extension": ""
      },
      "onlinePaymentsEnabled": true,
      "onlineOrderingEnabled": false,
      "pharmacyHours": {
        "sundayClose": "18:00",
        "sundayOpen": "11:00",
        "sundayHours": "",
        "mondayClose": "21:00",
        "mondayOpen": "09:00",
        "mondayHours": "",
        "tuesdayClose": "21:00",
        "tuesdayOpen": "09:00",
        "tuesdayHours": "",
        "wednesdayClose": "21:00",
        "wednesdayOpen": "09:00",
        "wednesdayHours": "",
        "thursdayClose": "21:00",
        "thursdayOpen": "09:00",
        "thursdayHours": "",
        "fridayClose": "21:00",
        "fridayOpen": "09:00",
        "fridayHours": "",
        "saturdayClose": "18:00",
        "saturdayOpen": "10:00",
        "saturdayHours": ""
      },
      "brand": "KROGER"
    },
    "dates": [
      {
        "date": "2021-03-18",
        "slots": []
      },
      {
        "date": "2021-03-19",
        "slots": []
      },
      {
        "date": "2021-03-20",
        "slots": []
      },
      {
        "date": "2021-03-21",
        "slots": []
      },
      {
        "date": "2021-03-22",
        "slots": []
      },
      {
        "date": "2021-03-23",
        "slots": []
      },
      {
        "date": "2021-03-24",
        "slots": []
      },
      {
        "date": "2021-03-25",
        "slots": []
      },
      {
        "date": "2021-03-26",
        "slots": []
      },
      {
        "date": "2021-03-27",
        "slots": []
      },
      {
        "date": "2021-03-28",
        "slots": []
      },
      {
        "date": "2021-03-29",
        "slots": []
      },
      {
        "date": "2021-03-30",
        "slots": []
      },
      {
        "date": "2021-03-31",
        "slots": []
      },
      {
        "date": "2021-04-01",
        "slots": []
      }
    ]
  },
  {
    "loc_id": 918,
    "loc_no": "01400439",
    "facilityDetails": {
      "facilityId": "01400439",
      "legalName": "Kroger Limited Partnership I",
      "vanityName": "Kyles Station",
      "address": {
        "address1": "5250 Newtown Drive",
        "address2": "",
        "city": "Liberty Township",
        "state": "OH",
        "zipCode": "45011"
      },
      "distance": 9.38013182872281,
      "phone": {
        "countryCode": "",
        "areaCode": "513",
        "phoneNumber": "8675420",
        "extension": ""
      },
      "onlinePaymentsEnabled": true,
      "onlineOrderingEnabled": false,
      "pharmacyHours": {
        "sundayClose": "18:00",
        "sundayOpen": "11:00",
        "sundayHours": "",
        "mondayClose": "21:00",
        "mondayOpen": "09:00",
        "mondayHours": "",
        "tuesdayClose": "21:00",
        "tuesdayOpen": "09:00",
        "tuesdayHours": "",
        "wednesdayClose": "21:00",
        "wednesdayOpen": "09:00",
        "wednesdayHours": "",
        "thursdayClose": "21:00",
        "thursdayOpen": "09:00",
        "thursdayHours": "",
        "fridayClose": "21:00",
        "fridayOpen": "09:00",
        "fridayHours": "",
        "saturdayClose": "18:00",
        "saturdayOpen": "10:00",
        "saturdayHours": ""
      },
      "brand": "KROGER"
    },
    "dates": [
      {
        "date": "2021-03-18",
        "slots": []
      },
      {
        "date": "2021-03-19",
        "slots": []
      },
      {
        "date": "2021-03-20",
        "slots": []
      },
      {
        "date": "2021-03-21",
        "slots": []
      },
      {
        "date": "2021-03-22",
        "slots": []
      },
      {
        "date": "2021-03-23",
        "slots": []
      },
      {
        "date": "2021-03-24",
        "slots": []
      },
      {
        "date": "2021-03-25",
        "slots": []
      },
      {
        "date": "2021-03-26",
        "slots": []
      },
      {
        "date": "2021-03-27",
        "slots": []
      },
      {
        "date": "2021-03-28",
        "slots": []
      },
      {
        "date": "2021-03-29",
        "slots": []
      },
      {
        "date": "2021-03-30",
        "slots": []
      },
      {
        "date": "2021-03-31",
        "slots": []
      },
      {
        "date": "2021-04-01",
        "slots": []
      }
    ]
  },
  {
    "loc_id": 929,
    "loc_no": "01400448",
    "facilityDetails": {
      "facilityId": "01400448",
      "legalName": "Kroger Limited Partnership I",
      "vanityName": "Mason Montgomery, Mason, OH",
      "address": {
        "address1": "5100 Terra Firma Dr",
        "address2": "",
        "city": "Mason",
        "state": "OH",
        "zipCode": "45040"
      },
      "distance": 1.8707951579530846,
      "phone": {
        "countryCode": "",
        "areaCode": "513",
        "phoneNumber": "2295920",
        "extension": ""
      },
      "onlinePaymentsEnabled": true,
      "onlineOrderingEnabled": false,
      "pharmacyHours": {
        "sundayClose": "18:00",
        "sundayOpen": "10:00",
        "sundayHours": "",
        "mondayClose": "21:00",
        "mondayOpen": "09:00",
        "mondayHours": "",
        "tuesdayClose": "21:00",
        "tuesdayOpen": "09:00",
        "tuesdayHours": "",
        "wednesdayClose": "21:00",
        "wednesdayOpen": "09:00",
        "wednesdayHours": "",
        "thursdayClose": "21:00",
        "thursdayOpen": "09:00",
        "thursdayHours": "",
        "fridayClose": "21:00",
        "fridayOpen": "09:00",
        "fridayHours": "",
        "saturdayClose": "18:00",
        "saturdayOpen": "10:00",
        "saturdayHours": ""
      },
      "brand": "KROGER"
    },
    "dates": [
      {
        "date": "2021-03-18",
        "slots": []
      },
      {
        "date": "2021-03-19",
        "slots": []
      },
      {
        "date": "2021-03-20",
        "slots": []
      },
      {
        "date": "2021-03-21",
        "slots": []
      },
      {
        "date": "2021-03-22",
        "slots": []
      },
      {
        "date": "2021-03-23",
        "slots": []
      },
      {
        "date": "2021-03-24",
        "slots": []
      },
      {
        "date": "2021-03-25",
        "slots": []
      },
      {
        "date": "2021-03-26",
        "slots": []
      },
      {
        "date": "2021-03-27",
        "slots": []
      },
      {
        "date": "2021-03-28",
        "slots": []
      },
      {
        "date": "2021-03-29",
        "slots": []
      },
      {
        "date": "2021-03-30",
        "slots": []
      },
      {
        "date": "2021-03-31",
        "slots": []
      },
      {
        "date": "2021-04-01",
        "slots": []
      }
    ]
  },
  {
    "loc_id": 971,
    "loc_no": "01400942",
    "facilityDetails": {
      "facilityId": "01400942",
      "legalName": "Kroger Limited Partnership I",
      "vanityName": "Blue Ash",
      "address": {
        "address1": "4100 Hunt Rd",
        "address2": "",
        "city": "Blue Ash",
        "state": "OH",
        "zipCode": "45236"
      },
      "distance": 9.321832489961745,
      "phone": {
        "countryCode": "",
        "areaCode": "513",
        "phoneNumber": "7921501",
        "extension": ""
      },
      "onlinePaymentsEnabled": true,
      "onlineOrderingEnabled": false,
      "pharmacyHours": {
        "sundayClose": "18:00",
        "sundayOpen": "11:00",
        "sundayHours": "",
        "mondayClose": "21:00",
        "mondayOpen": "09:00",
        "mondayHours": "",
        "tuesdayClose": "21:00",
        "tuesdayOpen": "09:00",
        "tuesdayHours": "",
        "wednesdayClose": "21:00",
        "wednesdayOpen": "09:00",
        "wednesdayHours": "",
        "thursdayClose": "21:00",
        "thursdayOpen": "09:00",
        "thursdayHours": "",
        "fridayClose": "21:00",
        "fridayOpen": "09:00",
        "fridayHours": "",
        "saturdayClose": "18:00",
        "saturdayOpen": "10:00",
        "saturdayHours": ""
      },
      "brand": "KROGER"
    },
    "dates": [
      {
        "date": "2021-03-18",
        "slots": []
      },
      {
        "date": "2021-03-19",
        "slots": []
      },
      {
        "date": "2021-03-20",
        "slots": []
      },
      {
        "date": "2021-03-21",
        "slots": []
      },
      {
        "date": "2021-03-22",
        "slots": []
      },
      {
        "date": "2021-03-23",
        "slots": []
      },
      {
        "date": "2021-03-24",
        "slots": []
      },
      {
        "date": "2021-03-25",
        "slots": []
      },
      {
        "date": "2021-03-26",
        "slots": []
      },
      {
        "date": "2021-03-27",
        "slots": []
      },
      {
        "date": "2021-03-28",
        "slots": []
      },
      {
        "date": "2021-03-29",
        "slots": []
      },
      {
        "date": "2021-03-30",
        "slots": []
      },
      {
        "date": "2021-03-31",
        "slots": []
      },
      {
        "date": "2021-04-01",
        "slots": []
      }
    ]
  },
  {
    "loc_id": 974,
    "loc_no": "01400945",
    "facilityDetails": {
      "facilityId": "01400945",
      "legalName": "Kroger Limited Partnership I",
      "vanityName": "Tylersville Road, West Chester, OH",
      "address": {
        "address1": "7855 Tylersville Rd",
        "address2": "",
        "city": "West Chester",
        "state": "OH",
        "zipCode": "45069"
      },
      "distance": 2.728636705920489,
      "phone": {
        "countryCode": "",
        "areaCode": "513",
        "phoneNumber": "7777393",
        "extension": ""
      },
      "onlinePaymentsEnabled": true,
      "onlineOrderingEnabled": false,
      "pharmacyHours": {
        "sundayClose": "18:00",
        "sundayOpen": "11:00",
        "sundayHours": "",
        "mondayClose": "21:00",
        "mondayOpen": "09:00",
        "mondayHours": "",
        "tuesdayClose": "21:00",
        "tuesdayOpen": "09:00",
        "tuesdayHours": "",
        "wednesdayClose": "21:00",
        "wednesdayOpen": "09:00",
        "wednesdayHours": "",
        "thursdayClose": "21:00",
        "thursdayOpen": "09:00",
        "thursdayHours": "",
        "fridayClose": "21:00",
        "fridayOpen": "09:00",
        "fridayHours": "",
        "saturdayClose": "18:00",
        "saturdayOpen": "10:00",
        "saturdayHours": ""
      },
      "brand": "KROGER"
    },
    "dates": [
      {
        "date": "2021-03-18",
        "slots": []
      },
      {
        "date": "2021-03-19",
        "slots": []
      },
      {
        "date": "2021-03-20",
        "slots": []
      },
      {
        "date": "2021-03-21",
        "slots": []
      },
      {
        "date": "2021-03-22",
        "slots": []
      },
      {
        "date": "2021-03-23",
        "slots": []
      },
      {
        "date": "2021-03-24",
        "slots": []
      },
      {
        "date": "2021-03-25",
        "slots": []
      },
      {
        "date": "2021-03-26",
        "slots": []
      },
      {
        "date": "2021-03-27",
        "slots": []
      },
      {
        "date": "2021-03-28",
        "slots": []
      },
      {
        "date": "2021-03-29",
        "slots": []
      },
      {
        "date": "2021-03-30",
        "slots": []
      },
      {
        "date": "2021-03-31",
        "slots": []
      },
      {
        "date": "2021-04-01",
        "slots": []
      }
    ]
  },
  {
    "loc_id": 978,
    "loc_no": "01400959",
    "facilityDetails": {
      "facilityId": "01400959",
      "legalName": "Kroger Limited Partnership I",
      "vanityName": "Crossings of Beckett",
      "address": {
        "address1": "8000 Princeton-Glendale Rd.",
        "address2": "",
        "city": "West Chester",
        "state": "OH",
        "zipCode": "45069"
      },
      "distance": 7.82865089316824,
      "phone": {
        "countryCode": "",
        "areaCode": "513",
        "phoneNumber": "6828040",
        "extension": ""
      },
      "onlinePaymentsEnabled": true,
      "onlineOrderingEnabled": false,
      "pharmacyHours": {
        "sundayClose": "18:00",
        "sundayOpen": "10:00",
        "sundayHours": "",
        "mondayClose": "21:00",
        "mondayOpen": "09:00",
        "mondayHours": "",
        "tuesdayClose": "21:00",
        "tuesdayOpen": "09:00",
        "tuesdayHours": "",
        "wednesdayClose": "21:00",
        "wednesdayOpen": "09:00",
        "wednesdayHours": "",
        "thursdayClose": "21:00",
        "thursdayOpen": "09:00",
        "thursdayHours": "",
        "fridayClose": "21:00",
        "fridayOpen": "09:00",
        "fridayHours": "",
        "saturdayClose": "18:00",
        "saturdayOpen": "10:00",
        "saturdayHours": ""
      },
      "brand": "KROGER"
    },
    "dates": [
      {
        "date": "2021-03-18",
        "slots": []
      },
      {
        "date": "2021-03-19",
        "slots": []
      },
      {
        "date": "2021-03-20",
        "slots": []
      },
      {
        "date": "2021-03-21",
        "slots": []
      },
      {
        "date": "2021-03-22",
        "slots": []
      },
      {
        "date": "2021-03-23",
        "slots": []
      },
      {
        "date": "2021-03-24",
        "slots": []
      },
      {
        "date": "2021-03-25",
        "slots": []
      },
      {
        "date": "2021-03-26",
        "slots": []
      },
      {
        "date": "2021-03-27",
        "slots": []
      },
      {
        "date": "2021-03-28",
        "slots": []
      },
      {
        "date": "2021-03-29",
        "slots": []
      },
      {
        "date": "2021-03-30",
        "slots": []
      },
      {
        "date": "2021-03-31",
        "slots": []
      },
      {
        "date": "2021-04-01",
        "slots": []
      }
    ]
  }
]